cpgeo/__init__.py
cpgeo/base.py
cpgeo/dlls/CPGEO.dll
cpgeo/dlls/src/CPGEO/CPGEO.vcxproj
cpgeo/dlls/src/CPGEO/CPGEO.vcxproj.filters
cpgeo/dlls/src/CPGEO/CPGEO.vcxproj.user
cpgeo/dlls/src/CPGEO/dllmain.cpp
cpgeo/dlls/src/CPGEO/flip_edges.cpp
cpgeo/dlls/src/CPGEO/framework.h
cpgeo/dlls/src/CPGEO/get_indices.cpp
cpgeo/dlls/src/CPGEO/get_indices_2nd.cpp
cpgeo/dlls/src/CPGEO/get_thresholds.cpp
cpgeo/dlls/src/CPGEO/packages.config
cpgeo/dlls/src/CPGEO/pch.cpp
cpgeo/dlls/src/CPGEO/pch.h
cpgeo/dlls/src/CPGEO/triangular_mesh.cpp
cpgeo/surface/Cylinder copy.py
cpgeo/surface/Cylinder.py
cpgeo/surface/Plane.py
cpgeo/surface/Sphere.py
cpgeo/surface/Sphere_Symmetry.py
cpgeo/surface/__init__.py
cpgeo/surface/base.py
cpgeo/utils/C_api.py
cpgeo/utils/__init__.py
cpgeo/utils/derivatives.py
cpgeo/utils/mesh.py
cpgeo/utils/mlab_visualization.py
cpgeo/utils/sparse.py
cpgeo-0.1.1.dist-info/METADATA
cpgeo-0.1.1.dist-info/WHEEL
cpgeo-0.1.1.dist-info/top_level.txt
cpgeo-0.1.1.dist-info/RECORD
