Metadata-Version: 2.4
Name: cpgeo
Version: 0.1.1
Summary: A library for control points-based surface.
Requires-Python: >=3.12
Requires-Dist: torch>=2.2.0
Requires-Dist: torchvision>=0.17.0
Requires-Dist: pypardiso>=0.4.7
Requires-Dist: scipy>=1.16.3
Requires-Dist: pyvista>=0.43.0
